{"teams":[{"team":{,"YEARID":"1963","LGID":"AL","TEAMID":"BAL","FRANCHID":"BAL","DIVID":"","RANK":"4","G":"162","GHOME":"81","W":"86","L":"76","DIVWIN":"","WCWIN":"","LGWIN":"N","WSWIN":"N","R":"644","AB":"5448","H":"1359","X2B":"207","X3B":"32","HR":"146","BB":"469","SO":"940","SB":"97","CS":"34","HBP":"-1","SF":"-1","RA":"621","ER":"557","ERA":"3.45","CG":"35","SHO":"8","SV":"43","IPOUTS":"4356","HA":"1353","HRA":"137","BBA":"507","SOA":"913","E":"99","DP":"157","FP":"0.98","NAME":"Baltimore Orioles","PARK":"Memorial Stadium","ATTENDANCE":"774343","BPF":"96","PPF":"95","TEAMIDBR":"BAL","TEAMIDLAHMAN45":"BAL","TEAMIDRETRO":"BAL"}},{"team":{,"YEARID":"1963","LGID":"AL","TEAMID":"BOS","FRANCHID":"BOS","DIVID":"","RANK":"7","G":"161","GHOME":"80","W":"76","L":"85","DIVWIN":"","WCWIN":"","LGWIN":"N","WSWIN":"N","R":"666","AB":"5575","H":"1403","X2B":"247","X3B":"34","HR":"171","BB":"475","SO":"954","SB":"27","CS":"16","HBP":"-1","SF":"-1","RA":"704","ER":"639","ERA":"3.97","CG":"29","SHO":"7","SV":"32","IPOUTS":"4347","HA":"1367","HRA":"152","BBA":"539","SOA":"1009","E":"132","DP":"119","FP":"0.97","NAME":"Boston Red Sox","PARK":"Fenway Park II","ATTENDANCE":"942642","BPF":"103","PPF":"104","TEAMIDBR":"BOS","TEAMIDLAHMAN45":"BOS","TEAMIDRETRO":"BOS"}},{"team":{,"YEARID":"1963","LGID":"AL","TEAMID":"CHA","FRANCHID":"CHW","DIVID":"","RANK":"2","G":"162","GHOME":"82","W":"94","L":"68","DIVWIN":"","WCWIN":"","LGWIN":"N","WSWIN":"N","R":"683","AB":"5508","H":"1379","X2B":"208","X3B":"40","HR":"114","BB":"571","SO":"896","SB":"64","CS":"28","HBP":"-1","SF":"-1","RA":"544","ER":"485","ERA":"2.97","CG":"49","SHO":"21","SV":"39","IPOUTS":"4407","HA":"1311","HRA":"100","BBA":"440","SOA":"932","E":"130","DP":"163","FP":"0.97","NAME":"Chicago White Sox","PARK":"Comiskey Park","ATTENDANCE":"1158848","BPF":"98","PPF":"96","TEAMIDBR":"CHW","TEAMIDLAHMAN45":"CHA","TEAMIDRETRO":"CHA"}},{"team":{,"YEARID":"1963","LGID":"NL","TEAMID":"CHN","FRANCHID":"CHC","DIVID":"","RANK":"7","G":"162","GHOME":"81","W":"82","L":"80","DIVWIN":"","WCWIN":"","LGWIN":"N","WSWIN":"N","R":"570","AB":"5404","H":"1286","X2B":"205","X3B":"44","HR":"127","BB":"439","SO":"1049","SB":"68","CS":"60","HBP":"-1","SF":"-1","RA":"578","ER":"499","ERA":"3.08","CG":"45","SHO":"15","SV":"28","IPOUTS":"4371","HA":"1357","HRA":"119","BBA":"400","SOA":"851","E":"155","DP":"172","FP":"0.97","NAME":"Chicago Cubs","PARK":"Wrigley Field","ATTENDANCE":"979551","BPF":"106","PPF":"107","TEAMIDBR":"CHC","TEAMIDLAHMAN45":"CHN","TEAMIDRETRO":"CHN"}},{"team":{,"YEARID":"1963","LGID":"NL","TEAMID":"CIN","FRANCHID":"CIN","DIVID":"","RANK":"5","G":"162","GHOME":"81","W":"86","L":"76","DIVWIN":"","WCWIN":"","LGWIN":"N","WSWIN":"N","R":"648","AB":"5416","H":"1333","X2B":"225","X3B":"44","HR":"122","BB":"474","SO":"960","SB":"92","CS":"58","HBP":"-1","SF":"-1","RA":"594","ER":"526","ERA":"3.29","CG":"55","SHO":"22","SV":"36","IPOUTS":"4317","HA":"1307","HRA":"117","BBA":"425","SOA":"1048","E":"135","DP":"127","FP":"0.97","NAME":"Cincinnati Reds","PARK":"Crosley Field","ATTENDANCE":"858805","BPF":"103","PPF":"102","TEAMIDBR":"CIN","TEAMIDLAHMAN45":"CIN","TEAMIDRETRO":"CIN"}},{"team":{,"YEARID":"1963","LGID":"AL","TEAMID":"CLE","FRANCHID":"CLE","DIVID":"","RANK":"5","G":"162","GHOME":"81","W":"79","L":"83","DIVWIN":"","WCWIN":"","LGWIN":"N","WSWIN":"N","R":"635","AB":"5496","H":"1314","X2B":"214","X3B":"29","HR":"169","BB":"469","SO":"1102","SB":"59","CS":"36","HBP":"-1","SF":"-1","RA":"702","ER":"619","ERA":"3.79","CG":"40","SHO":"14","SV":"25","IPOUTS":"4407","HA":"1390","HRA":"176","BBA":"478","SOA":"1018","E":"143","DP":"129","FP":"0.97","NAME":"Cleveland Indians","PARK":"Cleveland Stadium","ATTENDANCE":"562507","BPF":"100","PPF":"100","TEAMIDBR":"CLE","TEAMIDLAHMAN45":"CLE","TEAMIDRETRO":"CLE"}},{"team":{,"YEARID":"1963","LGID":"AL","TEAMID":"DET","FRANCHID":"DET","DIVID":"","RANK":"5","G":"162","GHOME":"81","W":"79","L":"83","DIVWIN":"","WCWIN":"","LGWIN":"N","WSWIN":"N","R":"700","AB":"5500","H":"1388","X2B":"195","X3B":"36","HR":"148","BB":"592","SO":"908","SB":"73","CS":"32","HBP":"-1","SF":"-1","RA":"703","ER":"631","ERA":"3.9","CG":"42","SHO":"7","SV":"28","IPOUTS":"4368","HA":"1407","HRA":"195","BBA":"477","SOA":"930","E":"113","DP":"124","FP":"0.98","NAME":"Detroit Tigers","PARK":"Tiger Stadium","ATTENDANCE":"821952","BPF":"103","PPF":"103","TEAMIDBR":"DET","TEAMIDLAHMAN45":"DET","TEAMIDRETRO":"DET"}},{"team":{,"YEARID":"1963","LGID":"NL","TEAMID":"HOU","FRANCHID":"HOU","DIVID":"","RANK":"9","G":"162","GHOME":"81","W":"66","L":"96","DIVWIN":"","WCWIN":"","LGWIN":"N","WSWIN":"N","R":"464","AB":"5384","H":"1184","X2B":"170","X3B":"39","HR":"62","BB":"456","SO":"938","SB":"39","CS":"30","HBP":"-1","SF":"-1","RA":"640","ER":"554","ERA":"3.44","CG":"36","SHO":"16","SV":"20","IPOUTS":"4350","HA":"1341","HRA":"95","BBA":"378","SOA":"937","E":"162","DP":"100","FP":"0.97","NAME":"Houston Colt .45's","PARK":"Colt Stadium","ATTENDANCE":"719502","BPF":"94","PPF":"96","TEAMIDBR":"HOU","TEAMIDLAHMAN45":"HOU","TEAMIDRETRO":"HOU"}},{"team":{,"YEARID":"1963","LGID":"AL","TEAMID":"KC1","FRANCHID":"OAK","DIVID":"","RANK":"8","G":"162","GHOME":"81","W":"73","L":"89","DIVWIN":"","WCWIN":"","LGWIN":"N","WSWIN":"N","R":"615","AB":"5495","H":"1356","X2B":"225","X3B":"38","HR":"95","BB":"529","SO":"829","SB":"47","CS":"26","HBP":"-1","SF":"-1","RA":"704","ER":"635","ERA":"3.92","CG":"35","SHO":"11","SV":"29","IPOUTS":"4374","HA":"1417","HRA":"156","BBA":"540","SOA":"887","E":"124","DP":"131","FP":"0.98","NAME":"Kansas City Athletics","PARK":"Municipal Stadium I","ATTENDANCE":"762364","BPF":"106","PPF":"108","TEAMIDBR":"KCA","TEAMIDLAHMAN45":"KC1","TEAMIDRETRO":"KC1"}},{"team":{,"YEARID":"1963","LGID":"AL","TEAMID":"LAA","FRANCHID":"ANA","DIVID":"","RANK":"9","G":"161","GHOME":"81","W":"70","L":"91","DIVWIN":"","WCWIN":"","LGWIN":"N","WSWIN":"N","R":"597","AB":"5506","H":"1378","X2B":"208","X3B":"38","HR":"95","BB":"448","SO":"916","SB":"43","CS":"30","HBP":"-1","SF":"-1","RA":"660","ER":"569","ERA":"3.52","CG":"30","SHO":"13","SV":"31","IPOUTS":"4365","HA":"1317","HRA":"120","BBA":"578","SOA":"889","E":"163","DP":"155","FP":"0.97","NAME":"Los Angeles Angels","PARK":"Dodger Stadium","ATTENDANCE":"821015","BPF":"94","PPF":"94","TEAMIDBR":"LAA","TEAMIDLAHMAN45":"LAA","TEAMIDRETRO":"LAA"}},{"team":{,"YEARID":"1963","LGID":"NL","TEAMID":"LAN","FRANCHID":"LAD","DIVID":"","RANK":"1","G":"163","GHOME":"81","W":"99","L":"63","DIVWIN":"","WCWIN":"","LGWIN":"Y","WSWIN":"Y","R":"640","AB":"5428","H":"1361","X2B":"178","X3B":"34","HR":"110","BB":"453","SO":"867","SB":"124","CS":"70","HBP":"-1","SF":"-1","RA":"550","ER":"465","ERA":"2.85","CG":"51","SHO":"24","SV":"29","IPOUTS":"4407","HA":"1329","HRA":"111","BBA":"402","SOA":"1095","E":"158","DP":"129","FP":"0.97","NAME":"Los Angeles Dodgers","PARK":"Dodger Stadium","ATTENDANCE":"2538602","BPF":"93","PPF":"91","TEAMIDBR":"LAD","TEAMIDLAHMAN45":"LAN","TEAMIDRETRO":"LAN"}},{"team":{,"YEARID":"1963","LGID":"AL","TEAMID":"MIN","FRANCHID":"MIN","DIVID":"","RANK":"3","G":"161","GHOME":"81","W":"91","L":"70","DIVWIN":"","WCWIN":"","LGWIN":"N","WSWIN":"N","R":"767","AB":"5531","H":"1408","X2B":"223","X3B":"35","HR":"225","BB":"547","SO":"912","SB":"32","CS":"14","HBP":"-1","SF":"-1","RA":"602","ER":"527","ERA":"3.28","CG":"58","SHO":"13","SV":"30","IPOUTS":"4338","HA":"1322","HRA":"162","BBA":"459","SOA":"941","E":"144","DP":"140","FP":"0.97","NAME":"Minnesota Twins","PARK":"Metropolitan Stadium","ATTENDANCE":"1406652","BPF":"102","PPF":"101","TEAMIDBR":"MIN","TEAMIDLAHMAN45":"MIN","TEAMIDRETRO":"MIN"}},{"team":{,"YEARID":"1963","LGID":"NL","TEAMID":"ML1","FRANCHID":"ATL","DIVID":"","RANK":"6","G":"163","GHOME":"82","W":"84","L":"78","DIVWIN":"","WCWIN":"","LGWIN":"N","WSWIN":"N","R":"677","AB":"5518","H":"1345","X2B":"204","X3B":"39","HR":"139","BB":"525","SO":"954","SB":"75","CS":"52","HBP":"-1","SF":"-1","RA":"603","ER":"534","ERA":"3.27","CG":"56","SHO":"18","SV":"25","IPOUTS":"4413","HA":"1327","HRA":"149","BBA":"489","SOA":"924","E":"129","DP":"161","FP":"0.98","NAME":"Milwaukee Braves","PARK":"County Stadium","ATTENDANCE":"773018","BPF":"99","PPF":"98","TEAMIDBR":"MLN","TEAMIDLAHMAN45":"MLN","TEAMIDRETRO":"MLN"}},{"team":{,"YEARID":"1963","LGID":"AL","TEAMID":"NYA","FRANCHID":"NYY","DIVID":"","RANK":"1","G":"161","GHOME":"80","W":"104","L":"57","DIVWIN":"","WCWIN":"","LGWIN":"Y","WSWIN":"N","R":"714","AB":"5506","H":"1387","X2B":"197","X3B":"35","HR":"188","BB":"434","SO":"808","SB":"42","CS":"26","HBP":"-1","SF":"-1","RA":"547","ER":"494","ERA":"3.07","CG":"59","SHO":"19","SV":"31","IPOUTS":"4347","HA":"1239","HRA":"115","BBA":"476","SOA":"965","E":"108","DP":"162","FP":"0.98","NAME":"New York Yankees","PARK":"Yankee Stadium I","ATTENDANCE":"1308920","BPF":"100","PPF":"97","TEAMIDBR":"NYY","TEAMIDLAHMAN45":"NYA","TEAMIDRETRO":"NYA"}},{"team":{,"YEARID":"1963","LGID":"NL","TEAMID":"NYN","FRANCHID":"NYM","DIVID":"","RANK":"10","G":"162","GHOME":"81","W":"51","L":"111","DIVWIN":"","WCWIN":"","LGWIN":"N","WSWIN":"N","R":"501","AB":"5336","H":"1168","X2B":"156","X3B":"35","HR":"96","BB":"457","SO":"1078","SB":"41","CS":"52","HBP":"-1","SF":"-1","RA":"774","ER":"653","ERA":"4.12","CG":"42","SHO":"5","SV":"12","IPOUTS":"4281","HA":"1452","HRA":"162","BBA":"529","SOA":"806","E":"208","DP":"151","FP":"0.96","NAME":"New York Mets","PARK":"Polo Grounds IV","ATTENDANCE":"1080108","BPF":"100","PPF":"105","TEAMIDBR":"NYM","TEAMIDLAHMAN45":"NYN","TEAMIDRETRO":"NYN"}},{"team":{,"YEARID":"1963","LGID":"NL","TEAMID":"PHI","FRANCHID":"PHI","DIVID":"","RANK":"4","G":"162","GHOME":"81","W":"87","L":"75","DIVWIN":"","WCWIN":"","LGWIN":"N","WSWIN":"N","R":"642","AB":"5524","H":"1390","X2B":"228","X3B":"54","HR":"126","BB":"403","SO":"955","SB":"56","CS":"39","HBP":"-1","SF":"-1","RA":"578","ER":"500","ERA":"3.09","CG":"45","SHO":"12","SV":"31","IPOUTS":"4371","HA":"1262","HRA":"113","BBA":"553","SOA":"1052","E":"142","DP":"147","FP":"0.97","NAME":"Philadelphia Phillies","PARK":"Connie Mack Stadium","ATTENDANCE":"907141","BPF":"99","PPF":"99","TEAMIDBR":"PHI","TEAMIDLAHMAN45":"PHI","TEAMIDRETRO":"PHI"}},{"team":{,"YEARID":"1963","LGID":"NL","TEAMID":"PIT","FRANCHID":"PIT","DIVID":"","RANK":"8","G":"162","GHOME":"81","W":"74","L":"88","DIVWIN":"","WCWIN":"","LGWIN":"N","WSWIN":"N","R":"567","AB":"5536","H":"1385","X2B":"181","X3B":"49","HR":"108","BB":"454","SO":"940","SB":"57","CS":"41","HBP":"-1","SF":"-1","RA":"595","ER":"499","ERA":"3.1","CG":"34","SHO":"16","SV":"33","IPOUTS":"4344","HA":"1350","HRA":"99","BBA":"457","SOA":"900","E":"182","DP":"195","FP":"0.97","NAME":"Pittsburgh Pirates","PARK":"Forbes Field","ATTENDANCE":"783648","BPF":"101","PPF":"100","TEAMIDBR":"PIT","TEAMIDLAHMAN45":"PIT","TEAMIDRETRO":"PIT"}},{"team":{,"YEARID":"1963","LGID":"NL","TEAMID":"SFN","FRANCHID":"SFG","DIVID":"","RANK":"3","G":"162","GHOME":"81","W":"88","L":"74","DIVWIN":"","WCWIN":"","LGWIN":"N","WSWIN":"N","R":"725","AB":"5579","H":"1442","X2B":"206","X3B":"35","HR":"197","BB":"441","SO":"889","SB":"55","CS":"49","HBP":"-1","SF":"-1","RA":"641","ER":"547","ERA":"3.35","CG":"46","SHO":"9","SV":"30","IPOUTS":"4407","HA":"1380","HRA":"126","BBA":"464","SOA":"954","E":"156","DP":"113","FP":"0.97","NAME":"San Francisco Giants","PARK":"Candlestick Park","ATTENDANCE":"1571306","BPF":"99","PPF":"97","TEAMIDBR":"SFG","TEAMIDLAHMAN45":"SFN","TEAMIDRETRO":"SFN"}},{"team":{,"YEARID":"1963","LGID":"NL","TEAMID":"SLN","FRANCHID":"STL","DIVID":"","RANK":"2","G":"162","GHOME":"81","W":"93","L":"69","DIVWIN":"","WCWIN":"","LGWIN":"N","WSWIN":"N","R":"747","AB":"5678","H":"1540","X2B":"231","X3B":"66","HR":"128","BB":"458","SO":"915","SB":"77","CS":"42","HBP":"-1","SF":"-1","RA":"628","ER":"540","ERA":"3.32","CG":"49","SHO":"17","SV":"32","IPOUTS":"4389","HA":"1329","HRA":"124","BBA":"463","SOA":"978","E":"147","DP":"136","FP":"0.97","NAME":"St. Louis Cardinals","PARK":"Sportsman's Park IV","ATTENDANCE":"1170546","BPF":"110","PPF":"109","TEAMIDBR":"STL","TEAMIDLAHMAN45":"SLN","TEAMIDRETRO":"SLN"}},{"team":{,"YEARID":"1963","LGID":"AL","TEAMID":"WS2","FRANCHID":"TEX","DIVID":"","RANK":"10","G":"162","GHOME":"80","W":"56","L":"106","DIVWIN":"","WCWIN":"","LGWIN":"N","WSWIN":"N","R":"578","AB":"5446","H":"1237","X2B":"190","X3B":"35","HR":"138","BB":"497","SO":"963","SB":"68","CS":"28","HBP":"-1","SF":"-1","RA":"812","ER":"711","ERA":"4.42","CG":"29","SHO":"8","SV":"25","IPOUTS":"4341","HA":"1486","HRA":"176","BBA":"537","SOA":"744","E":"182","DP":"165","FP":"0.97","NAME":"Washington Senators","PARK":"R.F.K. Stadium","ATTENDANCE":"535604","BPF":"100","PPF":"103","TEAMIDBR":"WSA","TEAMIDLAHMAN45":"WS2","TEAMIDRETRO":"WS2"}}]